{"nm":"2 - Responsive design","ddd":0,"h":200,"w":200,"meta":{"g":"LottieFiles AE 0.1.20"},"layers":[{"ty":4,"nm":"Block 1","sr":1,"st":0,"op":150,"ip":0,"hd":false,"ddd":0,"bm":0,"hasMask":false,"ao":0,"ks":{"a":{"a":0,"k":[49.978,26.75,0],"ix":1},"s":{"a":1,"k":[{"o":{"x":0.5,"y":0},"i":{"x":0.5,"y":1},"s":[0,100,100],"t":43},{"o":{"x":0.5,"y":0},"i":{"x":0.5,"y":1},"s":[110,100,100],"t":59},{"o":{"x":0.5,"y":0},"i":{"x":0.5,"y":1},"s":[90,100,100],"t":75},{"o":{"x":0.5,"y":0},"i":{"x":0.833,"y":1},"s":[100,100,100],"t":91},{"o":{"x":0.167,"y":0},"i":{"x":0.833,"y":1},"s":[100,100,100],"t":123},{"s":[100,0,100],"t":147}],"ix":6},"sk":{"a":0,"k":0},"p":{"a":1,"k":[{"o":{"x":0.5,"y":0},"i":{"x":0.5,"y":1},"s":[71.969,50,0],"t":86,"ti":[0,0,0],"to":[0,0,0]},{"o":{"x":0.5,"y":0},"i":{"x":0.5,"y":1},"s":[71.969,133,0],"t":107,"ti":[0,0,0],"to":[0,0,0]},{"s":[71.969,123,0],"t":123}],"ix":2},"r":{"a":0,"k":0,"ix":10},"sa":{"a":0,"k":0},"o":{"a":0,"k":100,"ix":11}},"ef":[],"shapes":[{"ty":"gr","bm":0,"hd":false,"mn":"ADBE Vector Group","nm":"Group 1","ix":1,"cix":2,"np":2,"it":[{"ty":"sh","bm":0,"hd":false,"mn":"ADBE Vector Shape - Group","nm":"Path 1","ix":1,"d":1,"ks":{"a":0,"k":{"c":true,"i":[[0,0],[0,0],[0,0],[0,0]],"o":[[0,0],[0,0],[0,0],[0,0]],"v":[[49.728,26.5],[-49.728,26.5],[-49.728,-26.5],[49.728,-26.5]]},"ix":2}},{"ty":"fl","bm":0,"hd":false,"mn":"ADBE Vector Graphic - Fill","nm":"Fill 1","c":{"a":0,"k":[0.3294,0.1608,0.702],"ix":4,"x":"var $bm_rt;\ntry {\n    $bm_rt = thisComp.layer('Controller').effect('Color')('ADBE Color Control-0001');\n} catch (e) {\n    $bm_rt = value;\n}"},"r":1,"o":{"a":0,"k":100,"ix":5}},{"ty":"tr","a":{"a":0,"k":[0,0],"ix":1},"s":{"a":0,"k":[100,100],"ix":3},"sk":{"a":0,"k":0,"ix":4},"p":{"a":0,"k":[49.978,26.75],"ix":2},"r":{"a":0,"k":0,"ix":6},"sa":{"a":0,"k":0,"ix":5},"o":{"a":0,"k":100,"ix":7}}]}],"ind":1,"parent":4},{"ty":4,"nm":"Block 2","sr":1,"st":0,"op":150,"ip":0,"hd":false,"ddd":0,"bm":0,"hasMask":false,"ao":0,"ks":{"a":{"a":0,"k":[49.978,26.75,0],"ix":1},"s":{"a":1,"k":[{"o":{"x":0.5,"y":0},"i":{"x":0.5,"y":1},"s":[0,100,100],"t":43},{"o":{"x":0.5,"y":0},"i":{"x":0.5,"y":1},"s":[110,100,100],"t":59},{"o":{"x":0.5,"y":0},"i":{"x":0.5,"y":1},"s":[90,100,100],"t":75},{"o":{"x":0.5,"y":0},"i":{"x":0.833,"y":1},"s":[100,100,100],"t":91},{"o":{"x":0.167,"y":0},"i":{"x":0.833,"y":1},"s":[100,100,100],"t":123},{"s":[100,0,100],"t":147}],"ix":6},"sk":{"a":0,"k":0},"p":{"a":1,"k":[{"o":{"x":0.5,"y":0},"i":{"x":0.5,"y":1},"s":[71.969,123,0],"t":86,"ti":[0,0,0],"to":[0,0,0]},{"o":{"x":0.5,"y":0},"i":{"x":0.5,"y":1},"s":[71.969,40,0],"t":107,"ti":[0,0,0],"to":[0,0,0]},{"s":[71.969,50,0],"t":123}],"ix":2},"r":{"a":0,"k":0,"ix":10},"sa":{"a":0,"k":0},"o":{"a":0,"k":100,"ix":11}},"ef":[],"shapes":[{"ty":"gr","bm":0,"hd":false,"mn":"ADBE Vector Group","nm":"Group 1","ix":1,"cix":2,"np":2,"it":[{"ty":"sh","bm":0,"hd":false,"mn":"ADBE Vector Shape - Group","nm":"Path 1","ix":1,"d":1,"ks":{"a":0,"k":{"c":true,"i":[[0,0],[0,0],[0,0],[0,0]],"o":[[0,0],[0,0],[0,0],[0,0]],"v":[[49.728,26.5],[-49.728,26.5],[-49.728,-26.5],[49.728,-26.5]]},"ix":2}},{"ty":"fl","bm":0,"hd":false,"mn":"ADBE Vector Graphic - Fill","nm":"Fill 1","c":{"a":0,"k":[1,0.5569,0.2275],"ix":4,"x":"var $bm_rt;\ntry {\n    $bm_rt = thisComp.layer('Controller').effect('Color 2')('ADBE Color Control-0001');\n} catch (e) {\n    $bm_rt = value;\n}"},"r":1,"o":{"a":0,"k":100,"ix":5}},{"ty":"tr","a":{"a":0,"k":[0,0],"ix":1},"s":{"a":0,"k":[100,100],"ix":3},"sk":{"a":0,"k":0,"ix":4},"p":{"a":0,"k":[49.978,26.75],"ix":2},"r":{"a":0,"k":0,"ix":6},"sa":{"a":0,"k":0,"ix":5},"o":{"a":0,"k":100,"ix":7}}]}],"ind":2,"parent":4},{"ty":4,"nm":"Button Tablet","sr":1,"st":0,"op":150,"ip":0,"hd":false,"ddd":0,"bm":0,"hasMask":false,"ao":0,"ks":{"a":{"a":0,"k":[5.742,5.776,0],"ix":1},"s":{"a":0,"k":[100,100,100],"ix":6},"sk":{"a":0,"k":0},"p":{"a":0,"k":[71.71,183.894,0],"ix":2},"r":{"a":0,"k":0,"ix":10},"sa":{"a":0,"k":0},"o":{"a":0,"k":100,"ix":11}},"ef":[],"shapes":[{"ty":"gr","bm":0,"hd":false,"mn":"ADBE Vector Group","nm":"Group 1","ix":1,"cix":2,"np":2,"it":[{"ty":"sh","bm":0,"hd":false,"mn":"ADBE Vector Shape - Group","nm":"Path 1","ix":1,"d":1,"ks":{"a":0,"k":{"c":true,"i":[[0,-3.052],[-3.033,0],[0,3.052],[3.033,0]],"o":[[0,3.052],[3.033,0],[0,-3.052],[-3.033,0]],"v":[[-5.492,0],[0,5.526],[5.492,0],[0,-5.526]]},"ix":2}},{"ty":"fl","bm":0,"hd":false,"mn":"ADBE Vector Graphic - Fill","nm":"Fill 1","c":{"a":0,"k":[1,0.6706,0.4196],"ix":4,"x":"var $bm_rt;\ntry {\n    $bm_rt = thisComp.layer('Controller').effect('Color 3')('ADBE Color Control-0001');\n} catch (e) {\n    $bm_rt = value;\n}"},"r":1,"o":{"a":0,"k":100,"ix":5}},{"ty":"tr","a":{"a":0,"k":[0,0],"ix":1},"s":{"a":0,"k":[100,100],"ix":3},"sk":{"a":0,"k":0,"ix":4},"p":{"a":0,"k":[5.742,5.776],"ix":2},"r":{"a":0,"k":0,"ix":6},"sa":{"a":0,"k":0,"ix":5},"o":{"a":0,"k":100,"ix":7}}]}],"ind":3,"parent":4},{"ty":4,"nm":"Tablet","sr":1,"st":0,"op":150,"ip":0,"hd":false,"ddd":0,"bm":0,"hasMask":false,"ao":0,"ks":{"a":{"a":0,"k":[71.709,197.74,0],"ix":1},"s":{"a":0,"k":[40,40,100],"ix":6},"sk":{"a":0,"k":0},"p":{"a":1,"k":[{"o":{"x":0.5,"y":0},"i":{"x":0.5,"y":1},"s":[142,156,0],"t":0},{"o":{"x":0.5,"y":0},"i":{"x":0.5,"y":1},"s":[146,156,0],"t":13},{"o":{"x":0.5,"y":0},"i":{"x":0.5,"y":1},"s":[138,156,0],"t":26},{"s":[142,156,0],"t":39}],"ix":2},"r":{"a":0,"k":0,"ix":10},"sa":{"a":0,"k":0},"o":{"a":0,"k":100,"ix":11}},"ef":[],"shapes":[{"ty":"gr","bm":0,"hd":false,"mn":"ADBE Vector Group","nm":"Group 1","ix":1,"cix":2,"np":2,"it":[{"ty":"sh","bm":0,"hd":false,"mn":"ADBE Vector Shape - Group","nm":"Path 1","ix":1,"d":1,"ks":{"a":0,"k":{"c":true,"i":[[0,0],[0,0],[0,0],[3.021,0],[0,0],[0,3.02]],"o":[[0,0],[0,0],[0,3.02],[0,0],[-3.021,0],[0,0]],"v":[[-71.459,-13.673],[71.459,-13.673],[71.459,8.205],[65.99,13.673],[-65.99,13.673],[-71.459,8.205]]},"ix":2}},{"ty":"fl","bm":0,"hd":false,"mn":"ADBE Vector Graphic - Fill","nm":"Fill 1","c":{"a":0,"k":[0.302,0.1882,0.5529],"ix":4,"x":"var $bm_rt;\ntry {\n    $bm_rt = thisComp.layer('Controller').effect('Color 4')('ADBE Color Control-0001');\n} catch (e) {\n    $bm_rt = value;\n}"},"r":1,"o":{"a":0,"k":100,"ix":5}},{"ty":"tr","a":{"a":0,"k":[0,0],"ix":1},"s":{"a":0,"k":[100,100],"ix":3},"sk":{"a":0,"k":0,"ix":4},"p":{"a":0,"k":[71.709,184.066],"ix":2},"r":{"a":0,"k":0,"ix":6},"sa":{"a":0,"k":0,"ix":5},"o":{"a":0,"k":100,"ix":7}}]},{"ty":"gr","bm":0,"hd":false,"mn":"ADBE Vector Group","nm":"Group 2","ix":2,"cix":2,"np":2,"it":[{"ty":"sh","bm":0,"hd":false,"mn":"ADBE Vector Shape - Group","nm":"Path 1","ix":1,"d":1,"ks":{"a":0,"k":{"c":true,"i":[[-3.02,0],[0,0],[0,3.021],[0,0],[3.02,0],[0,0],[0,-3.021],[0,0]],"o":[[0,0],[3.02,0],[0,0],[0,-3.021],[0,0],[-3.02,0],[0,0],[0,3.021]],"v":[[-65.99,98.745],[65.991,98.745],[71.459,93.276],[71.459,-93.276],[65.991,-98.745],[-65.99,-98.745],[-71.459,-93.276],[-71.459,93.276]]},"ix":2}},{"ty":"fl","bm":0,"hd":false,"mn":"ADBE Vector Graphic - Fill","nm":"Fill 1","c":{"a":0,"k":[0.749,0.6784,0.902],"ix":4,"x":"var $bm_rt;\ntry {\n    $bm_rt = thisComp.layer('Controller').effect('Color 5')('ADBE Color Control-0001');\n} catch (e) {\n    $bm_rt = value;\n}"},"r":1,"o":{"a":0,"k":100,"ix":5}},{"ty":"tr","a":{"a":0,"k":[0,0],"ix":1},"s":{"a":0,"k":[100,100],"ix":3},"sk":{"a":0,"k":0,"ix":4},"p":{"a":0,"k":[71.709,98.995],"ix":2},"r":{"a":0,"k":0,"ix":6},"sa":{"a":0,"k":0,"ix":5},"o":{"a":0,"k":100,"ix":7}}]}],"ind":4},{"ty":4,"nm":"Block 1","sr":1,"st":0,"op":150,"ip":0,"hd":false,"ddd":0,"bm":0,"hasMask":false,"ao":0,"ks":{"a":{"a":0,"k":[33.75,17.5,0],"ix":1},"s":{"a":1,"k":[{"o":{"x":0.5,"y":0},"i":{"x":0.833,"y":1},"s":[0,100,100],"t":41},{"o":{"x":0.167,"y":0},"i":{"x":0.833,"y":1},"s":[110,100,100],"t":57},{"o":{"x":0.167,"y":0},"i":{"x":0.5,"y":1},"s":[90,100,100],"t":73},{"o":{"x":0.167,"y":0},"i":{"x":0.833,"y":1},"s":[100,100,100],"t":89},{"o":{"x":0.167,"y":0},"i":{"x":0.833,"y":1},"s":[100,100,100],"t":121},{"s":[100,0,100],"t":145}],"ix":6},"sk":{"a":0,"k":0},"p":{"a":1,"k":[{"o":{"x":0.5,"y":0},"i":{"x":0.5,"y":1},"s":[48,32,0],"t":84,"ti":[0,0,0],"to":[0,0,0]},{"o":{"x":0.167,"y":0},"i":{"x":0.5,"y":1},"s":[48,90,0],"t":105,"ti":[0,0,0],"to":[0,0,0]},{"s":[48,83,0],"t":121}],"ix":2},"r":{"a":0,"k":0,"ix":10},"sa":{"a":0,"k":0},"o":{"a":0,"k":100,"ix":11}},"ef":[],"shapes":[{"ty":"gr","bm":0,"hd":false,"mn":"ADBE Vector Group","nm":"Group 1","ix":1,"cix":2,"np":2,"it":[{"ty":"sh","bm":0,"hd":false,"mn":"ADBE Vector Shape - Group","nm":"Path 1","ix":1,"d":1,"ks":{"a":0,"k":{"c":true,"i":[[0,0],[0,0],[0,0],[0,0]],"o":[[0,0],[0,0],[0,0],[0,0]],"v":[[33.5,17.25],[-33.5,17.25],[-33.5,-17.25],[33.5,-17.25]]},"ix":2}},{"ty":"fl","bm":0,"hd":false,"mn":"ADBE Vector Graphic - Fill","nm":"Fill 1","c":{"a":0,"k":[0.3294,0.1608,0.702],"ix":4,"x":"var $bm_rt;\ntry {\n    $bm_rt = thisComp.layer('Controller')('Effects')('Color')('ADBE Color Control-0001');\n} catch (e) {\n    $bm_rt = value;\n}"},"r":1,"o":{"a":0,"k":100,"ix":5}},{"ty":"tr","a":{"a":0,"k":[0,0],"ix":1},"s":{"a":0,"k":[100,100],"ix":3},"sk":{"a":0,"k":0,"ix":4},"p":{"a":0,"k":[33.75,17.5],"ix":2},"r":{"a":0,"k":0,"ix":6},"sa":{"a":0,"k":0,"ix":5},"o":{"a":0,"k":100,"ix":7}}]}],"ind":5,"parent":8},{"ty":4,"nm":"Block 2","sr":1,"st":0,"op":150,"ip":0,"hd":false,"ddd":0,"bm":0,"hasMask":false,"ao":0,"ks":{"a":{"a":0,"k":[33.75,17.5,0],"ix":1},"s":{"a":1,"k":[{"o":{"x":0.5,"y":0},"i":{"x":0.833,"y":1},"s":[0,100,100],"t":41},{"o":{"x":0.167,"y":0},"i":{"x":0.833,"y":1},"s":[110,100,100],"t":57},{"o":{"x":0.167,"y":0},"i":{"x":0.5,"y":1},"s":[90,100,100],"t":73},{"o":{"x":0.167,"y":0},"i":{"x":0.833,"y":1},"s":[100,100,100],"t":89},{"o":{"x":0.167,"y":0},"i":{"x":0.833,"y":1},"s":[100,100,100],"t":121},{"s":[100,0,100],"t":145}],"ix":6},"sk":{"a":0,"k":0},"p":{"a":1,"k":[{"o":{"x":0.5,"y":0},"i":{"x":0.5,"y":1},"s":[48,83,0],"t":84,"ti":[0,0,0],"to":[0,0,0]},{"o":{"x":0.167,"y":0},"i":{"x":0.5,"y":1},"s":[48,27,0],"t":105,"ti":[0,0,0],"to":[0,0,0]},{"s":[48,32,0],"t":121}],"ix":2},"r":{"a":0,"k":0,"ix":10},"sa":{"a":0,"k":0},"o":{"a":0,"k":100,"ix":11}},"ef":[],"shapes":[{"ty":"gr","bm":0,"hd":false,"mn":"ADBE Vector Group","nm":"Group 1","ix":1,"cix":2,"np":2,"it":[{"ty":"sh","bm":0,"hd":false,"mn":"ADBE Vector Shape - Group","nm":"Path 1","ix":1,"d":1,"ks":{"a":0,"k":{"c":true,"i":[[0,0],[0,0],[0,0],[0,0]],"o":[[0,0],[0,0],[0,0],[0,0]],"v":[[33.5,17.25],[-33.5,17.25],[-33.5,-17.25],[33.5,-17.25]]},"ix":2}},{"ty":"fl","bm":0,"hd":false,"mn":"ADBE Vector Graphic - Fill","nm":"Fill 1","c":{"a":0,"k":[1,0.5569,0.2275],"ix":4,"x":"var $bm_rt;\ntry {\n    $bm_rt = thisComp.layer('Controller')('Effects')('Color 2')('ADBE Color Control-0001');\n} catch (e) {\n    $bm_rt = value;\n}"},"r":1,"o":{"a":0,"k":100,"ix":5}},{"ty":"tr","a":{"a":0,"k":[0,0],"ix":1},"s":{"a":0,"k":[100,100],"ix":3},"sk":{"a":0,"k":0,"ix":4},"p":{"a":0,"k":[33.75,17.5],"ix":2},"r":{"a":0,"k":0,"ix":6},"sa":{"a":0,"k":0,"ix":5},"o":{"a":0,"k":100,"ix":7}}]}],"ind":6,"parent":8},{"ty":4,"nm":"Button Phone","sr":1,"st":0,"op":150,"ip":0,"hd":false,"ddd":0,"bm":0,"hasMask":false,"ao":0,"ks":{"a":{"a":0,"k":[5.742,5.776,0],"ix":1},"s":{"a":0,"k":[100,100,100],"ix":6},"sk":{"a":0,"k":0},"p":{"a":0,"k":[48.609,128.591,0],"ix":2},"r":{"a":0,"k":0,"ix":10},"sa":{"a":0,"k":0},"o":{"a":0,"k":100,"ix":11}},"ef":[],"shapes":[{"ty":"gr","bm":0,"hd":false,"mn":"ADBE Vector Group","nm":"Group 1","ix":1,"cix":2,"np":2,"it":[{"ty":"sh","bm":0,"hd":false,"mn":"ADBE Vector Shape - Group","nm":"Path 1","ix":1,"d":1,"ks":{"a":0,"k":{"c":true,"i":[[0,-3.052],[-3.033,0],[0,3.052],[3.033,0]],"o":[[0,3.052],[3.033,0],[0,-3.052],[-3.033,0]],"v":[[-5.492,0],[0,5.526],[5.492,0],[0,-5.526]]},"ix":2}},{"ty":"fl","bm":0,"hd":false,"mn":"ADBE Vector Graphic - Fill","nm":"Fill 1","c":{"a":0,"k":[1,0.5569,0.2275],"ix":4,"x":"var $bm_rt;\ntry {\n    $bm_rt = thisComp.layer('Controller')('Effects')('Color 3')('ADBE Color Control-0001');\n} catch (e) {\n    $bm_rt = value;\n}"},"r":1,"o":{"a":0,"k":100,"ix":5}},{"ty":"tr","a":{"a":0,"k":[0,0],"ix":1},"s":{"a":0,"k":[100,100],"ix":3},"sk":{"a":0,"k":0,"ix":4},"p":{"a":0,"k":[5.742,5.776],"ix":2},"r":{"a":0,"k":0,"ix":6},"sa":{"a":0,"k":0,"ix":5},"o":{"a":0,"k":100,"ix":7}}]}],"ind":7,"parent":8},{"ty":4,"nm":"Phone","sr":1,"st":0,"op":150,"ip":0,"hd":false,"ddd":0,"bm":0,"hasMask":false,"ao":0,"ks":{"a":{"a":0,"k":[48.609,142.437,0],"ix":1},"s":{"a":0,"k":[40,40,100],"ix":6},"sk":{"a":0,"k":0},"p":{"a":1,"k":[{"o":{"x":0.5,"y":0},"i":{"x":0.5,"y":1},"s":[50,156,0],"t":0},{"o":{"x":0.5,"y":0},"i":{"x":0.5,"y":1},"s":[46,156,0],"t":13},{"o":{"x":0.5,"y":0},"i":{"x":0.5,"y":1},"s":[54,156,0],"t":26},{"s":[50,156,0],"t":39}],"ix":2},"r":{"a":0,"k":0,"ix":10},"sa":{"a":0,"k":0},"o":{"a":0,"k":100,"ix":11}},"ef":[],"shapes":[{"ty":"gr","bm":0,"hd":false,"mn":"ADBE Vector Group","nm":"Group 1","ix":1,"cix":2,"np":2,"it":[{"ty":"sh","bm":0,"hd":false,"mn":"ADBE Vector Shape - Group","nm":"Path 1","ix":1,"d":1,"ks":{"a":0,"k":{"c":true,"i":[[0,0],[0,0],[0,0],[3.02,0],[0,0],[0,3.02]],"o":[[0,0],[0,0],[0,3.02],[0,0],[-3.021,0],[0,0]],"v":[[-48.359,-13.673],[48.359,-13.673],[48.359,8.205],[42.891,13.673],[-42.89,13.673],[-48.359,8.205]]},"ix":2}},{"ty":"fl","bm":0,"hd":false,"mn":"ADBE Vector Graphic - Fill","nm":"Fill 1","c":{"a":0,"k":[0.4157,0.2314,0.8078],"ix":4,"x":"var $bm_rt;\ntry {\n    $bm_rt = thisComp.layer('Controller')('Effects')('Color 4')('ADBE Color Control-0001');\n} catch (e) {\n    $bm_rt = value;\n}"},"r":1,"o":{"a":0,"k":100,"ix":5}},{"ty":"tr","a":{"a":0,"k":[0,0],"ix":1},"s":{"a":0,"k":[100,100],"ix":3},"sk":{"a":0,"k":0,"ix":4},"p":{"a":0,"k":[48.609,128.763],"ix":2},"r":{"a":0,"k":0,"ix":6},"sa":{"a":0,"k":0,"ix":5},"o":{"a":0,"k":100,"ix":7}}]},{"ty":"gr","bm":0,"hd":false,"mn":"ADBE Vector Group","nm":"Group 2","ix":2,"cix":2,"np":2,"it":[{"ty":"sh","bm":0,"hd":false,"mn":"ADBE Vector Shape - Group","nm":"Path 1","ix":1,"d":1,"ks":{"a":0,"k":{"c":true,"i":[[-3.02,0],[0,0],[0,3.021],[0,0],[3.02,0],[0,0],[0,-3.02],[0,0]],"o":[[0,0],[3.02,0],[0,0],[0,-3.02],[0,0],[-3.02,0],[0,0],[0,3.021]],"v":[[-42.89,71.094],[42.89,71.094],[48.359,65.625],[48.359,-65.626],[42.89,-71.094],[-42.89,-71.094],[-48.359,-65.626],[-48.359,65.625]]},"ix":2}},{"ty":"fl","bm":0,"hd":false,"mn":"ADBE Vector Graphic - Fill","nm":"Fill 1","c":{"a":0,"k":[0.8275,0.7686,0.9529],"ix":4,"x":"var $bm_rt;\ntry {\n    $bm_rt = thisComp.layer('Controller')('Effects')('Color 5')('ADBE Color Control-0001');\n} catch (e) {\n    $bm_rt = value;\n}"},"r":1,"o":{"a":0,"k":100,"ix":5}},{"ty":"tr","a":{"a":0,"k":[0,0],"ix":1},"s":{"a":0,"k":[100,100],"ix":3},"sk":{"a":0,"k":0,"ix":4},"p":{"a":0,"k":[48.609,71.344],"ix":2},"r":{"a":0,"k":0,"ix":6},"sa":{"a":0,"k":0,"ix":5},"o":{"a":0,"k":100,"ix":7}}]}],"ind":8},{"ty":4,"nm":"Block 1","sr":1,"st":0,"op":150,"ip":0,"hd":false,"ddd":0,"bm":0,"hasMask":false,"ao":0,"ks":{"a":{"a":0,"k":[125.693,32.645,0],"ix":1},"s":{"a":1,"k":[{"o":{"x":0.5,"y":0},"i":{"x":0.833,"y":1},"s":[0,100,100],"t":39},{"o":{"x":0.167,"y":0},"i":{"x":0.833,"y":1},"s":[110,100,100],"t":55},{"o":{"x":0.167,"y":0},"i":{"x":0.5,"y":1},"s":[95,100,100],"t":71},{"o":{"x":0.167,"y":0},"i":{"x":0.833,"y":1},"s":[100,100,100],"t":87},{"o":{"x":0.167,"y":0},"i":{"x":0.833,"y":1},"s":[100,100,100],"t":119},{"s":[100,0,100],"t":143}],"ix":6},"sk":{"a":0,"k":0},"p":{"a":1,"k":[{"o":{"x":0.5,"y":0},"i":{"x":0.5,"y":1},"s":[153,59,0],"t":82,"ti":[0,0,0],"to":[0,0,0]},{"o":{"x":0.167,"y":0},"i":{"x":0.5,"y":1},"s":[153,160,0],"t":103,"ti":[0,0,0],"to":[0,0,0]},{"s":[153,149,0],"t":119}],"ix":2},"r":{"a":0,"k":0,"ix":10},"sa":{"a":0,"k":0},"o":{"a":0,"k":100,"ix":11}},"ef":[],"shapes":[{"ty":"gr","bm":0,"hd":false,"mn":"ADBE Vector Group","nm":"Group 1","ix":1,"cix":2,"np":2,"it":[{"ty":"sh","bm":0,"hd":false,"mn":"ADBE Vector Shape - Group","nm":"Path 1","ix":1,"d":1,"ks":{"a":0,"k":{"c":true,"i":[[0,0],[0,0],[0,0],[0,0]],"o":[[0,0],[0,0],[0,0],[0,0]],"v":[[125.443,32.395],[-125.443,32.395],[-125.443,-32.395],[125.443,-32.395]]},"ix":2}},{"ty":"fl","bm":0,"hd":false,"mn":"ADBE Vector Graphic - Fill","nm":"Fill 1","c":{"a":0,"k":[0.3294,0.1608,0.702],"ix":4,"x":"var $bm_rt;\ntry {\n    $bm_rt = thisComp.layer('Controller')('Effects')('Color')('ADBE Color Control-0001');\n} catch (e) {\n    $bm_rt = value;\n}"},"r":1,"o":{"a":0,"k":100,"ix":5}},{"ty":"tr","a":{"a":0,"k":[0,0],"ix":1},"s":{"a":0,"k":[100,100],"ix":3},"sk":{"a":0,"k":0,"ix":4},"p":{"a":0,"k":[125.693,32.645],"ix":2},"r":{"a":0,"k":0,"ix":6},"sa":{"a":0,"k":0,"ix":5},"o":{"a":0,"k":100,"ix":7}}]}],"ind":9,"parent":12},{"ty":4,"nm":"Block 2","sr":1,"st":0,"op":150,"ip":0,"hd":false,"ddd":0,"bm":0,"hasMask":false,"ao":0,"ks":{"a":{"a":0,"k":[125.693,32.645,0],"ix":1},"s":{"a":1,"k":[{"o":{"x":0.5,"y":0},"i":{"x":0.833,"y":1},"s":[0,100,100],"t":39},{"o":{"x":0.167,"y":0},"i":{"x":0.833,"y":1},"s":[110,100,100],"t":55},{"o":{"x":0.167,"y":0},"i":{"x":0.5,"y":1},"s":[95,100,100],"t":71},{"o":{"x":0.167,"y":0},"i":{"x":0.833,"y":1},"s":[100,100,100],"t":87},{"o":{"x":0.167,"y":0},"i":{"x":0.833,"y":1},"s":[100,100,100],"t":119},{"s":[100,0,100],"t":143}],"ix":6},"sk":{"a":0,"k":0},"p":{"a":1,"k":[{"o":{"x":0.5,"y":0},"i":{"x":0.5,"y":1},"s":[153,149,0],"t":82,"ti":[0,0,0],"to":[0,0,0]},{"o":{"x":0.167,"y":0},"i":{"x":0.5,"y":1},"s":[153,50,0],"t":103,"ti":[0,0,0],"to":[0,0,0]},{"s":[153,59,0],"t":119}],"ix":2},"r":{"a":0,"k":0,"ix":10},"sa":{"a":0,"k":0},"o":{"a":0,"k":100,"ix":11}},"ef":[],"shapes":[{"ty":"gr","bm":0,"hd":false,"mn":"ADBE Vector Group","nm":"Group 1","ix":1,"cix":2,"np":2,"it":[{"ty":"sh","bm":0,"hd":false,"mn":"ADBE Vector Shape - Group","nm":"Path 1","ix":1,"d":1,"ks":{"a":0,"k":{"c":true,"i":[[0,0],[0,0],[0,0],[0,0]],"o":[[0,0],[0,0],[0,0],[0,0]],"v":[[125.443,32.395],[-125.443,32.395],[-125.443,-32.395],[125.443,-32.395]]},"ix":2}},{"ty":"fl","bm":0,"hd":false,"mn":"ADBE Vector Graphic - Fill","nm":"Fill 1","c":{"a":0,"k":[1,0.5569,0.2275],"ix":4,"x":"var $bm_rt;\ntry {\n    $bm_rt = thisComp.layer('Controller')('Effects')('Color 2')('ADBE Color Control-0001');\n} catch (e) {\n    $bm_rt = value;\n}"},"r":1,"o":{"a":0,"k":100,"ix":5}},{"ty":"tr","a":{"a":0,"k":[0,0],"ix":1},"s":{"a":0,"k":[100,100],"ix":3},"sk":{"a":0,"k":0,"ix":4},"p":{"a":0,"k":[125.693,32.645],"ix":2},"r":{"a":0,"k":0,"ix":6},"sa":{"a":0,"k":0,"ix":5},"o":{"a":0,"k":100,"ix":7}}]}],"ind":10,"parent":12},{"ty":4,"nm":"Button Computer","sr":1,"st":0,"op":150,"ip":0,"hd":false,"ddd":0,"bm":0,"hasMask":false,"ao":0,"ks":{"a":{"a":0,"k":[5.742,5.776,0],"ix":1},"s":{"a":0,"k":[100,100,100],"ix":6},"sk":{"a":0,"k":0},"p":{"a":0,"k":[153.373,223.591,0],"ix":2},"r":{"a":0,"k":0,"ix":10},"sa":{"a":0,"k":0},"o":{"a":0,"k":100,"ix":11}},"ef":[],"shapes":[{"ty":"gr","bm":0,"hd":false,"mn":"ADBE Vector Group","nm":"Group 1","ix":1,"cix":2,"np":2,"it":[{"ty":"sh","bm":0,"hd":false,"mn":"ADBE Vector Shape - Group","nm":"Path 1","ix":1,"d":1,"ks":{"a":0,"k":{"c":true,"i":[[0,-3.052],[-3.033,0],[0,3.052],[3.033,0]],"o":[[0,3.052],[3.033,0],[0,-3.052],[-3.033,0]],"v":[[-5.492,0],[0,5.526],[5.492,0],[0,-5.526]]},"ix":2}},{"ty":"fl","bm":0,"hd":false,"mn":"ADBE Vector Graphic - Fill","nm":"Fill 1","c":{"a":0,"k":[1,0.5569,0.2275],"ix":4,"x":"var $bm_rt;\ntry {\n    $bm_rt = thisComp.layer('Controller')('Effects')('Color 3')('ADBE Color Control-0001');\n} catch (e) {\n    $bm_rt = value;\n}"},"r":1,"o":{"a":0,"k":100,"ix":5}},{"ty":"tr","a":{"a":0,"k":[0,0],"ix":1},"s":{"a":0,"k":[100,100],"ix":3},"sk":{"a":0,"k":0,"ix":4},"p":{"a":0,"k":[5.742,5.776],"ix":2},"r":{"a":0,"k":0,"ix":6},"sa":{"a":0,"k":0,"ix":5},"o":{"a":0,"k":100,"ix":7}}]}],"ind":11,"parent":12},{"ty":4,"nm":"Computer","sr":1,"st":0,"op":150,"ip":0,"hd":false,"ddd":0,"bm":0,"hasMask":false,"ao":0,"ks":{"a":{"a":0,"k":[153.373,120.235,0],"ix":1},"s":{"a":0,"k":[40,40,100],"ix":6},"sk":{"a":0,"k":0},"p":{"a":0,"k":[100,92,0],"ix":2},"r":{"a":0,"k":0,"ix":10},"sa":{"a":0,"k":0},"o":{"a":0,"k":100,"ix":11}},"ef":[],"shapes":[{"ty":"gr","bm":0,"hd":false,"mn":"ADBE Vector Group","nm":"Group 1","ix":1,"cix":2,"np":2,"it":[{"ty":"sh","bm":0,"hd":false,"mn":"ADBE Vector Shape - Group","nm":"Path 1","ix":1,"d":1,"ks":{"a":0,"k":{"c":true,"i":[[0,0],[0,0],[0,0],[0,0]],"o":[[0,0],[0,0],[0,0],[0,0]],"v":[[153.123,16.408],[-153.123,16.408],[-153.123,-16.408],[153.123,-16.408]]},"ix":2}},{"ty":"fl","bm":0,"hd":false,"mn":"ADBE Vector Graphic - Fill","nm":"Fill 1","c":{"a":0,"k":[0.2392,0.2431,0],"ix":4,"x":"var $bm_rt;\ntry {\n    $bm_rt = thisComp.layer('Controller')('Effects')('Color 4')('ADBE Color Control-0001');\n} catch (e) {\n    $bm_rt = value;\n}"},"r":1,"o":{"a":0,"k":100,"ix":5}},{"ty":"tr","a":{"a":0,"k":[0,0],"ix":1},"s":{"a":0,"k":[100,100],"ix":3},"sk":{"a":0,"k":0,"ix":4},"p":{"a":0,"k":[153.373,223.813],"ix":2},"r":{"a":0,"k":0,"ix":6},"sa":{"a":0,"k":0,"ix":5},"o":{"a":0,"k":100,"ix":7}}]},{"ty":"gr","bm":0,"hd":false,"mn":"ADBE Vector Group","nm":"Group 2","ix":2,"cix":2,"np":2,"it":[{"ty":"sh","bm":0,"hd":false,"mn":"ADBE Vector Shape - Group","nm":"Path 1","ix":1,"d":1,"ks":{"a":0,"k":{"c":true,"i":[[0,0],[3.021,0],[0,0],[0,-3.02],[0,0],[0,0]],"o":[[0,-3.02],[0,0],[-3.02,0],[0,0],[0,0],[0,0]],"v":[[153.123,-114.516],[147.654,-119.984],[-147.654,-119.984],[-153.123,-114.516],[-153.123,119.984],[153.123,119.984]]},"ix":2}},{"ty":"fl","bm":0,"hd":false,"mn":"ADBE Vector Graphic - Fill","nm":"Fill 1","c":{"a":0,"k":[0.6118,0.451,0.9725],"ix":4,"x":"var $bm_rt;\ntry {\n    $bm_rt = thisComp.layer('Controller').effect('Color 6')('ADBE Color Control-0001');\n} catch (e) {\n    $bm_rt = value;\n}"},"r":1,"o":{"a":0,"k":100,"ix":5}},{"ty":"tr","a":{"a":0,"k":[0,0],"ix":1},"s":{"a":0,"k":[100,100],"ix":3},"sk":{"a":0,"k":0,"ix":4},"p":{"a":0,"k":[153.373,120.235],"ix":2},"r":{"a":0,"k":0,"ix":6},"sa":{"a":0,"k":0,"ix":5},"o":{"a":0,"k":100,"ix":7}}]}],"ind":12}],"v":"5.5.7","fr":30,"op":150,"ip":0,"assets":[]}